{
  "type": "pfm:furniture",
  "group": "kitchen",
  "ingredients": [
    {
      "item": "byg:stripped_pine_log"
    },
    {
      "item": "byg:stripped_pine_log"
    },
    {
      "item": "byg:stripped_pine_log"
    },
    {
      "item": "byg:stripped_pine_log"
    },
    {
      "item": "byg:stripped_pine_log"
    },
    {
      "item": "byg:stripped_pine_log"
    },
    {
      "item": "byg:stripped_pine_log"
    },
    {
      "item": "byg:stripped_pine_log"
    },
    {
      "item": "byg:stripped_pine_log"
    }
  ],
  "result": {
    "count": 6,
    "item": "pfm:stripped_pine_byg_kitchen_wall_counter"
  }
}